LICENSE
MANIFEST.in
README.rst
setup.cfg
setup.py
versioneer.py
tests/__init__.py
tests/test_general.py
tpRigToolkit/__init__.py
tpRigToolkit/tools/__init__.py
tpRigToolkit/tools/jointorient/__init__.py
tpRigToolkit/tools/jointorient/__logging__.ini
tpRigToolkit/tools/jointorient/__version__.py
tpRigToolkit/tools/jointorient/_version.py
tpRigToolkit/tools/jointorient/core/__init__.py
tpRigToolkit/tools/jointorient/core/client.py
tpRigToolkit/tools/jointorient/core/consts.py
tpRigToolkit/tools/jointorient/core/controller.py
tpRigToolkit/tools/jointorient/core/model.py
tpRigToolkit/tools/jointorient/core/tool.py
tpRigToolkit/tools/jointorient/core/toolset.py
tpRigToolkit/tools/jointorient/core/view.py
tpRigToolkit/tools/jointorient/dccs/__init__.py
tpRigToolkit/tools/jointorient/dccs/maya/__init__.py
tpRigToolkit/tools/jointorient/dccs/maya/server.py
tpRigToolkit/tools/jointorient/widgets/__init__.py
tpRigToolkit/tools/jointorient/widgets/jointorient.py
tpRigToolkit/tools/jointorient/widgets/jointutils.py
tpRigToolkit/tools/jointorient/widgets/manualjointorient.py
tpRigToolkit/tools/jointorient/widgets/rotationaxis.py
tpRigToolkit_tools_jointorient.egg-info/PKG-INFO
tpRigToolkit_tools_jointorient.egg-info/SOURCES.txt
tpRigToolkit_tools_jointorient.egg-info/dependency_links.txt
tpRigToolkit_tools_jointorient.egg-info/not-zip-safe
tpRigToolkit_tools_jointorient.egg-info/requires.txt
tpRigToolkit_tools_jointorient.egg-info/top_level.txt