Metadata-Version: 2.1
Name: tpRigToolkit-tools-jointorient
Version: 0.0.3
Summary: Tool to orient joints quickly
Home-page: https://github.com/tpRigToolkit/tpRigToolkit-tools-jointorient
Author: Tomas Poveda
Author-email: tpovedatd@gmail.com
License: MIT
Platform: UNKNOWN
Provides-Extra: dev
Provides-Extra: test
